hungovercoders_template_python_package/__init__.py
hungovercoders_template_python_package/greetings.py
hungovercoders_template_python_package/organisation.py
hungovercoders_template_python_package/py.typed
hungovercoders_template_python_package/schemas/organisation_schema.json
hungovercoders_template_python_package/schemas/teams_schema.json
hungovercoders_template_python_package-0.1.1.dist-info/METADATA
hungovercoders_template_python_package-0.1.1.dist-info/WHEEL
hungovercoders_template_python_package-0.1.1.dist-info/entry_points.txt
hungovercoders_template_python_package-0.1.1.dist-info/licenses/LICENSE
hungovercoders_template_python_package-0.1.1.dist-info/RECORD
