Metadata-Version: 2.4
Name: hungovercoders_template_python_package
Version: 0.1.1
Summary: This is a template for a Python package created by Hungover Coders.
Author-email: dataGriff <info@hungovercoders.com>
License: # MIT License
License-File: LICENSE
Requires-Python: >=3.12
